micromagnetictests/__init__.py
micromagnetictests/get_tests.py
micromagnetictests/calculatortests/__init__.py
micromagnetictests/calculatortests/compute.py
micromagnetictests/calculatortests/cubicanisotropy.py
micromagnetictests/calculatortests/damping.py
micromagnetictests/calculatortests/demag.py
micromagnetictests/calculatortests/dirname.py
micromagnetictests/calculatortests/dmi.py
micromagnetictests/calculatortests/dynamics.py
micromagnetictests/calculatortests/energy.py
micromagnetictests/calculatortests/exchange.py
micromagnetictests/calculatortests/fixedsubregions.py
micromagnetictests/calculatortests/hysteresisdriver.py
micromagnetictests/calculatortests/info_file.py
micromagnetictests/calculatortests/mesh.py
micromagnetictests/calculatortests/mindriver.py
micromagnetictests/calculatortests/multiple_drives.py
micromagnetictests/calculatortests/outputformat.py
micromagnetictests/calculatortests/outputstep.py
micromagnetictests/calculatortests/precession.py
micromagnetictests/calculatortests/relaxdriver.py
micromagnetictests/calculatortests/rkky.py
micromagnetictests/calculatortests/schedule.py
micromagnetictests/calculatortests/skyrmion.py
micromagnetictests/calculatortests/slonczewski.py
micromagnetictests/calculatortests/stdprob3.py
micromagnetictests/calculatortests/stdprob4.py
micromagnetictests/calculatortests/stdprob5.py
micromagnetictests/calculatortests/threads.py
micromagnetictests/calculatortests/timedriver.py
micromagnetictests/calculatortests/uniaxialanisotropy.py
micromagnetictests/calculatortests/zeeman.py
micromagnetictests/calculatortests/zhangli.py
micromagnetictests/tests/__init__.py
micromagnetictests/tests/test_get_tests.py
micromagnetictests/tests/test_init.py
micromagnetictests-0.64.0.dist-info/licenses/LICENSE
micromagnetictests-0.64.0.dist-info/METADATA
micromagnetictests-0.64.0.dist-info/WHEEL
micromagnetictests-0.64.0.dist-info/top_level.txt
micromagnetictests-0.64.0.dist-info/RECORD
