Metadata-Version: 2.4
Name: micromagnetictests
Version: 0.64.0
Summary: Testing package for computational magnetism tools.
Author: Marijan Beg, Martin Lang, Samuel Holt, Swapneel Amit Pathak, Hans Fangohr
License-Expression: BSD-3-Clause
Project-URL: homepage, https://ubermag.github.io
Project-URL: documentation, https://ubermag.github.io/documentation/micromagnetictests
Project-URL: repository, https://github.com/ubermag/micromagnetictests
Classifier: Development Status :: 5 - Production/Stable
Classifier: Intended Audience :: Education
Classifier: Intended Audience :: Developers
Classifier: Intended Audience :: Science/Research
Classifier: Natural Language :: English
Classifier: Operating System :: MacOS
Classifier: Operating System :: Microsoft :: Windows
Classifier: Operating System :: Unix
Classifier: Programming Language :: Python :: 3 :: Only
Classifier: Topic :: Scientific/Engineering :: Physics
Classifier: Topic :: Scientific/Engineering :: Mathematics
Classifier: Topic :: Scientific/Engineering :: Visualization
Requires-Python: >=3.9
License-File: LICENSE
Requires-Dist: micromagneticmodel>=0.65.0
Requires-Dist: micromagneticdata>=0.66.0
Requires-Dist: scipy>=1.5
Provides-Extra: dev
Requires-Dist: build; extra == "dev"
Requires-Dist: invoke; extra == "dev"
Requires-Dist: nbval; extra == "dev"
Requires-Dist: pre-commit; extra == "dev"
Requires-Dist: pytest-cov; extra == "dev"
Requires-Dist: twine; extra == "dev"
Requires-Dist: tomli; python_version < "3.11" and extra == "dev"
Dynamic: license-file
